Metadata-Version: 1.1
Name: dannyisalways
Version: 1.1
Summary: My first project
Home-page: https://github.com/ekils/dannyisalways
Author: ekils
Author-email: bobobo746@hotmail.com
License: UNKNOWN
Download-URL: https://github.com/ekils/dannyisalways.git
Keywords: Good Project
Platform: UNKNOWN
